lorettOrbital/__init__.py
lorettOrbital/orbital.py
lorettOrbital/exceptions/__init__.py
lorettOrbital/exceptions/exceptions.py
lorettOrbital/scheduler/__init__.py
lorettOrbital/scheduler/scheduler.py
lorettOrbital/tests/SchedulerUnitTest.py
lorettOrbital/tests/__init__.py
lorettOrbital-1.0.18042023.dist-info/LICENSE
lorettOrbital-1.0.18042023.dist-info/METADATA
lorettOrbital-1.0.18042023.dist-info/WHEEL
lorettOrbital-1.0.18042023.dist-info/top_level.txt
lorettOrbital-1.0.18042023.dist-info/RECORD
