Metadata-Version: 2.1
Name: lorettOrbital
Version: 1.0.18042023
Summary: LorettOrbital Python 3 library for orbital calculations and planning
Home-page: https://gitlab.com/lpmrfentazis/lorettorbital
Author: MrFentazis
Author-email: lpmrfentazis@mail.ru
License: MIT
Classifier: Programming Language :: Python :: 3.9
Classifier: License :: OSI Approved :: MIT License
Classifier: Operating System :: OS Independent
Requires-Python: >=3.9
License-File: LICENSE
Requires-Dist: requests (>=2.26.0)
Requires-Dist: pyorbital (>=1.6.1)
Requires-Dist: beautifulsoup4 (>=4.10.0)
Requires-Dist: prettytable (>=2.2.0)
Requires-Dist: verboseLogs (>=1.7)
